puretransport/__init__.py
puretransport/factory.py
puretransport/sasl_compat.py
pure_transport-0.2.0.dist-info/LICENSE
pure_transport-0.2.0.dist-info/METADATA
pure_transport-0.2.0.dist-info/WHEEL
pure_transport-0.2.0.dist-info/top_level.txt
pure_transport-0.2.0.dist-info/RECORD
