Metadata-Version: 2.1
Name: pure-transport
Version: 0.2.0
Summary: Pure Sasl Based Thrift Transport for PyHive
Home-page: https://github.com/devinstevenson/pure-transport
Author: Devin Stevenson
Author-email: UNKNOWN
License: GPLv3+
Keywords: pyhive
Platform: UNKNOWN
Classifier: Development Status :: 3 - Alpha
Classifier: Intended Audience :: Developers
Classifier: License :: OSI Approved :: MIT License
Classifier: Natural Language :: English
Classifier: Operating System :: OS Independent
Classifier: Programming Language :: Python :: 2.6
Classifier: Programming Language :: Python :: 2.7
Classifier: Programming Language :: Python :: 3.3
Classifier: Programming Language :: Python :: 3.4
Classifier: Topic :: Software Development :: Libraries :: Python Modules
Requires-Dist: thrift
Requires-Dist: pure-sasl (>=0.3.0)
Requires-Dist: thrift-sasl
